git_pylint_commit_hook/__init__.py
git_pylint_commit_hook/commit_hook.py
git_pylint_commit_hook/settings.conf
git_pylint_commit_hook-2.6.1.data/scripts/git-pylint-commit-hook
git_pylint_commit_hook-2.6.1.dist-info/LICENSE
git_pylint_commit_hook-2.6.1.dist-info/METADATA
git_pylint_commit_hook-2.6.1.dist-info/WHEEL
git_pylint_commit_hook-2.6.1.dist-info/top_level.txt
git_pylint_commit_hook-2.6.1.dist-info/RECORD
